pypager/__init__.py
pypager/__main__.py
pypager/filters.py
pypager/help.py
pypager/key_bindings.py
pypager/layout.py
pypager/pager.py
pypager/source.py
pypager/style.py
pypager/entry_points/__init__.py
pypager/entry_points/run_pypager.py
pypager-3.0.1.dist-info/LICENSE
pypager-3.0.1.dist-info/METADATA
pypager-3.0.1.dist-info/WHEEL
pypager-3.0.1.dist-info/entry_points.txt
pypager-3.0.1.dist-info/top_level.txt
pypager-3.0.1.dist-info/RECORD
