Metadata-Version: 2.1
Name: pypager
Version: 3.0.1
Summary: Pure Python pager (like "more" and "less").
Home-page: https://github.com/jonathanslenders/pypager
Author: Jonathan Slenders
License: LICENSE
Requires-Python: >=3.6
License-File: LICENSE
